odoo/addons/stock_picking_supplier_ref/README.rst
odoo/addons/stock_picking_supplier_ref/__init__.py
odoo/addons/stock_picking_supplier_ref/__manifest__.py
odoo/addons/stock_picking_supplier_ref/i18n/es.po
odoo/addons/stock_picking_supplier_ref/i18n/it.po
odoo/addons/stock_picking_supplier_ref/i18n/stock_picking_supplier_ref.pot
odoo/addons/stock_picking_supplier_ref/models/__init__.py
odoo/addons/stock_picking_supplier_ref/models/stock_picking.py
odoo/addons/stock_picking_supplier_ref/readme/CONTRIBUTORS.md
odoo/addons/stock_picking_supplier_ref/readme/DESCRIPTION.md
odoo/addons/stock_picking_supplier_ref/readme/HISTORY.md
odoo/addons/stock_picking_supplier_ref/readme/USAGE.md
odoo/addons/stock_picking_supplier_ref/static/description/icon.png
odoo/addons/stock_picking_supplier_ref/static/description/index.html
odoo/addons/stock_picking_supplier_ref/tests/__init__.py
odoo/addons/stock_picking_supplier_ref/tests/test_supplier_ref.py
odoo/addons/stock_picking_supplier_ref/views/stock_picking.xml
odoo_addon_stock_picking_supplier_ref-18.0.1.1.0.2.dist-info/METADATA
odoo_addon_stock_picking_supplier_ref-18.0.1.1.0.2.dist-info/WHEEL
odoo_addon_stock_picking_supplier_ref-18.0.1.1.0.2.dist-info/top_level.txt
odoo_addon_stock_picking_supplier_ref-18.0.1.1.0.2.dist-info/RECORD
