Metadata-Version: 2.1
Name: odoo-addon-stock_picking_supplier_ref
Version: 18.0.1.1.0.2
Requires-Python: >=3.10
Requires-Dist: odoo==18.0.*
Summary: Adds a supplier reference field inside supplier's pickings and allows search for this reference.
Home-page: https://github.com/OCA/stock-logistics-warehouse
License: AGPL-3
Author: Trey, Odoo Community Association (OCA)
Author-email: support@odoo-community.org
Classifier: Programming Language :: Python
Classifier: Framework :: Odoo
Classifier: Framework :: Odoo :: 18.0
Classifier: License :: OSI Approved :: GNU Affero General Public License v3
